saxproject/__init__.py
saxproject/api.py
saxproject/middleware.py
saxproject/orm.py
saxproject/response.py
saxproject-1.1.1.dist-info/LICENSE.md
saxproject-1.1.1.dist-info/WHEEL
saxproject-1.1.1.dist-info/METADATA
saxproject-1.1.1.dist-info/RECORD
