Metadata-Version: 2.1
Name: saxproject
Version: 1.1.1
Summary: 
Home-page: https://rise-consulting.github.io/saxproject/
Keywords: web framework,WSGI
Author: Massimiliano Bertinetti
Author-email: max-b@murena.io
Maintainer: Massimiliano Bertinetti
Maintainer-email: max-b@murena.io
Requires-Python: >=3.10,<4.0
Classifier: Development Status :: 5 - Production/Stable
Classifier: Environment :: Web Environment
Classifier: Intended Audience :: Developers
Classifier: License :: OSI Approved :: MIT License
Classifier: Operating System :: OS Independent
Classifier: Programming Language :: Python
Classifier: Programming Language :: Python :: 3
Classifier: Programming Language :: Python :: 3.10
Classifier: Programming Language :: Python :: 3.11
Classifier: Programming Language :: Python :: 3
Classifier: Programming Language :: Python :: 3 :: Only
Classifier: Programming Language :: Python :: 3.10
Classifier: Programming Language :: Python :: 3.11
Classifier: Topic :: Internet :: WWW/HTTP
Classifier: Topic :: Internet :: WWW/HTTP :: Dynamic Content
Classifier: Topic :: Internet :: WWW/HTTP :: WSGI
Classifier: Topic :: Software Development :: Libraries :: Application Frameworks
Requires-Dist: jinja2 (>=3.1.2,<4.0.0)
Requires-Dist: parse (>=1.19.0,<2.0.0)
Requires-Dist: requests (>=2.28.1,<3.0.0)
Requires-Dist: requests-wsgi-adapter (>=0.4.1,<0.5.0)
Requires-Dist: webob (>=1.8.7,<2.0.0)
Requires-Dist: whitenoise (>=6.3.0,<7.0.0)
Project-URL: Documentation, https://rise-consulting.github.io/saxproject/
